tensorflow_gnn-1.0.3.data/platlib/tensorflow_gnn/BUILD
tensorflow_gnn-1.0.3.data/platlib/tensorflow_gnn/__init__.py
tensorflow_gnn-1.0.3.data/platlib/tensorflow_gnn/version.py
tensorflow_gnn-1.0.3.data/platlib/tensorflow_gnn/api_def/api_symbols_test.py
tensorflow_gnn-1.0.3.data/platlib/tensorflow_gnn/converters/__init__.py
tensorflow_gnn-1.0.3.data/platlib/tensorflow_gnn/converters/networkx_io.py
tensorflow_gnn-1.0.3.data/platlib/tensorflow_gnn/converters/networkx_io_test.py
tensorflow_gnn-1.0.3.data/platlib/tensorflow_gnn/converters/triples.py
tensorflow_gnn-1.0.3.data/platlib/tensorflow_gnn/converters/triples_test.py
tensorflow_gnn-1.0.3.data/platlib/tensorflow_gnn/converters/ogb/__init__.py
tensorflow_gnn-1.0.3.data/platlib/tensorflow_gnn/converters/ogb/convert_ogb_dataset.py
tensorflow_gnn-1.0.3.data/platlib/tensorflow_gnn/converters/ogb/ogb_lib.py
tensorflow_gnn-1.0.3.data/platlib/tensorflow_gnn/data/BUILD
tensorflow_gnn-1.0.3.data/platlib/tensorflow_gnn/data/__init__.py
tensorflow_gnn-1.0.3.data/platlib/tensorflow_gnn/data/unigraph.py
tensorflow_gnn-1.0.3.data/platlib/tensorflow_gnn/data/unigraph_test.py
tensorflow_gnn-1.0.3.data/platlib/tensorflow_gnn/experimental/BUILD
tensorflow_gnn-1.0.3.data/platlib/tensorflow_gnn/experimental/__init__.py
tensorflow_gnn-1.0.3.data/platlib/tensorflow_gnn/experimental/datasets/BUILD
tensorflow_gnn-1.0.3.data/platlib/tensorflow_gnn/experimental/datasets/pyg_adapter.py
tensorflow_gnn-1.0.3.data/platlib/tensorflow_gnn/experimental/datasets/pyg_adapter_test.py
tensorflow_gnn-1.0.3.data/platlib/tensorflow_gnn/experimental/sampler/BUILD
tensorflow_gnn-1.0.3.data/platlib/tensorflow_gnn/experimental/sampler/__init__.py
tensorflow_gnn-1.0.3.data/platlib/tensorflow_gnn/experimental/sampler/core.py
tensorflow_gnn-1.0.3.data/platlib/tensorflow_gnn/experimental/sampler/core_test.py
tensorflow_gnn-1.0.3.data/platlib/tensorflow_gnn/experimental/sampler/custom_ops_test.py
tensorflow_gnn-1.0.3.dist-info/AUTHORS
tensorflow_gnn-1.0.3.dist-info/LICENSE
tensorflow_gnn-1.0.3.dist-info/METADATA
tensorflow_gnn-1.0.3.dist-info/WHEEL
tensorflow_gnn-1.0.3.dist-info/entry_points.txt
tensorflow_gnn-1.0.3.dist-info/namespace_packages.txt
tensorflow_gnn-1.0.3.dist-info/top_level.txt
tensorflow_gnn-1.0.3.dist-info/RECORD
