Metadata-Version: 2.1
Name: tensorflow-gnn
Version: 1.0.3
Summary: A library for building scalable graph neural networks in TensorFlow.
Home-page: https://github.com/tensorflow/gnn
Download-URL: https://github.com/tensorflow/gnn.git
Author: Google LLC
Author-email: tensorflow-gnn@googlegroups.com
License: Apache 2.0
Keywords: tensorflow gnn graph
Classifier: Development Status :: 5 - Production/Stable
Classifier: Intended Audience :: Developers
Classifier: Intended Audience :: Science/Research
Classifier: License :: OSI Approved :: Apache Software License
Classifier: Operating System :: MacOS :: MacOS X
Classifier: Operating System :: POSIX :: Linux
Classifier: Operating System :: Microsoft :: Windows
Classifier: Programming Language :: Python
Classifier: Programming Language :: Python :: 3
Classifier: Programming Language :: Python :: 3 :: Only
Classifier: Topic :: Scientific/Engineering
Classifier: Topic :: Scientific/Engineering :: Artificial Intelligence
Classifier: Topic :: Scientific/Engineering :: Mathematics
Classifier: Topic :: Software Development
Classifier: Topic :: Software Development :: Libraries
Classifier: Topic :: Software Development :: Libraries :: Python Modules
Requires-Python: >=3.8,<4
License-File: LICENSE
License-File: AUTHORS
Requires-Dist: apache-beam
Requires-Dist: google-vizier >=0.0.13
Requires-Dist: ml-collections
Requires-Dist: networkx
Requires-Dist: pyarrow
Requires-Dist: tensorflow <3,>=2.12.0 ; platform_machine != "arm64" or platform_system != "Darwin"
Requires-Dist: tensorflow-macos <3,>=2.12.0 ; platform_machine == "arm64" and platform_system == "Darwin"
